<?xml version="1.0" encoding="utf-8"?>
<Config>
  <LeagueNewRandom ID="1" Name="กลุ่มที่1" BeginNum="1" EndNum="10" />
  <LeagueNewRandom ID="2" Name="กลุ่มที่2" BeginNum="11" EndNum="20" />
  <LeagueNewRandom ID="3" Name="กลุ่มที่3" BeginNum="21" EndNum="30" />
  <LeagueNewRandom ID="4" Name="กลุ่มที่4" BeginNum="31" EndNum="40" />
  <LeagueNewRandom ID="5" Name="กลุ่มที่5" BeginNum="41" EndNum="50" />
  <LeagueNewRandom ID="6" Name="กลุ่มที่6" BeginNum="51" EndNum="100" />
  <LeagueNewRandom ID="7" Name="กลุ่มที่7" BeginNum="101" EndNum="150" />
  <LeagueNewRandom ID="8" Name="กลุ่มที่8" BeginNum="151" EndNum="200" />
  <LeagueNewRandom ID="9" Name="กลุ่มที่9" BeginNum="201" EndNum="-1" />
</Config>