<?xml version="1.0" encoding="utf-8"?>
<Config>
  <TreasureEvent ID="1001" Type="1" NewGoods="7050,3,1,0,0,0,0" NewValue="" NewDiec="" NewSuperDiec="" NeedGoods="" NeedValue="" Move="" FuBenID="" Box="" Descriptio="" Intro="Golden Relic Gift Box*3" />
  <TreasureEvent ID="1002" Type="1" NewGoods="5110,1,1,0,0,0,0" NewValue="" NewDiec="" NewSuperDiec="" NeedGoods="" NeedValue="" Move="" FuBenID="" Box="" Descriptio="" Intro="Aether Dust (100)" />
  <TreasureEvent ID="1003" Type="1" NewGoods="5120,1,1,0,0,0,0" NewValue="" NewDiec="" NewSuperDiec="" NeedGoods="" NeedValue="" Move="" FuBenID="" Box="" Descriptio="" Intro="Elemental Stone (30)" />
  <TreasureEvent ID="1004" Type="1" NewGoods="2017,1,1,0,0,0,0" NewValue="" NewDiec="" NewSuperDiec="" NeedGoods="" NeedValue="" Move="" FuBenID="" Box="" Descriptio="" Intro="Condor Flame" />
  <TreasureEvent ID="1005" Type="1" NewGoods="2030,1,1,0,0,0,0" NewValue="" NewDiec="" NewSuperDiec="" NeedGoods="" NeedValue="" Move="" FuBenID="" Box="" Descriptio="" Intro="Seed Jewel" />
  <TreasureEvent ID="1101" Type="1" NewGoods="" NewValue="" NewDiec="1" NewSuperDiec="" NeedGoods="" NeedValue="" Move="" FuBenID="" Box="" Descriptio="" Intro="1 Dice" />
  <TreasureEvent ID="1102" Type="1" NewGoods="" NewValue="" NewDiec="2" NewSuperDiec="" NeedGoods="" NeedValue="" Move="" FuBenID="" Box="" Descriptio="" Intro="2 Dice" />
  <TreasureEvent ID="1103" Type="1" NewGoods="" NewValue="" NewDiec="3" NewSuperDiec="" NeedGoods="" NeedValue="" Move="" FuBenID="" Box="" Descriptio="" Intro="3 Dice" />
  <TreasureEvent ID="1201" Type="1" NewGoods="" NewValue="" NewDiec="" NewSuperDiec="1" NeedGoods="" NeedValue="" Move="" FuBenID="" Box="" Descriptio="" Intro="1 Golden Dice" />
  <TreasureEvent ID="1202" Type="1" NewGoods="" NewValue="" NewDiec="" NewSuperDiec="2" NeedGoods="" NeedValue="" Move="" FuBenID="" Box="" Descriptio="" Intro="2 Golden Dice" />
  <TreasureEvent ID="1301" Type="1" NewGoods="" NewValue="111,1" NewDiec="" NewSuperDiec="" NeedGoods="" NeedValue="" Move="" FuBenID="" Box="" Descriptio="" Intro="1 Ruby" />
  <TreasureEvent ID="1302" Type="1" NewGoods="" NewValue="111,2" NewDiec="" NewSuperDiec="" NeedGoods="" NeedValue="" Move="" FuBenID="" Box="" Descriptio="" Intro="2 Ruby" />
  <TreasureEvent ID="1303" Type="1" NewGoods="" NewValue="111,5" NewDiec="" NewSuperDiec="" NeedGoods="" NeedValue="" Move="" FuBenID="" Box="" Descriptio="" Intro="5 Ruby" />
  <TreasureEvent ID="1304" Type="1" NewGoods="" NewValue="111,10" NewDiec="" NewSuperDiec="" NeedGoods="" NeedValue="" Move="" FuBenID="" Box="" Descriptio="" Intro="10 Ruby" />
  <TreasureEvent ID="1401" Type="1" NewGoods="" NewValue="110,10" NewDiec="" NewSuperDiec="" NeedGoods="" NeedValue="" Move="" FuBenID="" Box="" Descriptio="" Intro="10 Dice Point" />
  <TreasureEvent ID="1402" Type="1" NewGoods="" NewValue="110,20" NewDiec="" NewSuperDiec="" NeedGoods="" NeedValue="" Move="" FuBenID="" Box="" Descriptio="" Intro="20 Dice Point" />
  <TreasureEvent ID="1403" Type="1" NewGoods="" NewValue="110,50" NewDiec="" NewSuperDiec="" NeedGoods="" NeedValue="" Move="" FuBenID="" Box="" Descriptio="" Intro="50 Dice Point" />
  <TreasureEvent ID="2001" Type="2" NewGoods="2005,1,1,0,0,0,0" NewValue="" NewDiec="" NewSuperDiec="" NeedGoods="" NeedValue="111,15" Move="" FuBenID="" Box="" Descriptio="{fac60d}Trade : {17e43e}15 {fac60d}Ruby for {17e43e}Jewel of Guardian" Intro="Exchange Ruby for Jewel of Guardian" />
  <TreasureEvent ID="2002" Type="2" NewGoods="5031,1,1,0,0,0,0" NewValue="" NewDiec="" NewSuperDiec="" NeedGoods="" NeedValue="111,8" Move="" FuBenID="" Box="" Descriptio="{fac60d}Trade : {17e43e}8 {fac60d}Ruby for {17e43e}Superior Achievement Badge" Intro="Exchange Ruby for Superior Achievement Badge" />
  <TreasureEvent ID="2003" Type="2" NewGoods="5041,1,1,0,0,0,0" NewValue="" NewDiec="" NewSuperDiec="" NeedGoods="" NeedValue="111,8" Move="" FuBenID="" Box="" Descriptio="{fac60d}Trade : {17e43e}8 {fac60d}Ruby for {17e43e}Superior Fame Badge" Intro="Exchange Ruby for Superior Fame Badge" />
  <TreasureEvent ID="2004" Type="2" NewGoods="7004,1,1,0,0,0,0" NewValue="" NewDiec="" NewSuperDiec="" NeedGoods="" NeedValue="111,8" Move="" FuBenID="" Box="" Descriptio="{fac60d}Trade : {17e43e}8 {fac60d}Ruby for {17e43e}Epic Chest Ticket" Intro="Exchange Ruby for Epic Chest Ticket" />
  <TreasureEvent ID="2005" Type="2" NewGoods="7005,1,1,0,0,0,0" NewValue="" NewDiec="" NewSuperDiec="" NeedGoods="" NeedValue="111,8" Move="" FuBenID="" Box="" Descriptio="{fac60d}Trade : {17e43e}8 {fac60d}Ruby for {17e43e}Epic Pet Ticket" Intro="Exchange Ruby for Epic Pet Ticket" />
  <TreasureEvent ID="2006" Type="2" NewGoods="5150,1,1,0,0,0,0" NewValue="" NewDiec="" NewSuperDiec="" NeedGoods="" NeedValue="111,8" Move="" FuBenID="" Box="" Descriptio="{fac60d}Trade : {17e43e}8 {fac60d}Ruby for {17e43e}Medal of Honor" Intro="Exchange Ruby for Medal of Honor" />
  <TreasureEvent ID="2101" Type="2" NewGoods="2005,1,1,0,0,0,0" NewValue="" NewDiec="" NewSuperDiec="" NeedGoods="" NeedValue="110,240" Move="" FuBenID="" Box="" Descriptio="{fac60d}Trade : {17e43e}240 {fac60d}Dice Point for {17e43e}Jewel of Guardian" Intro="Exchange Point for Jewel of Guardian" />
  <TreasureEvent ID="2102" Type="2" NewGoods="5031,1,1,0,0,0,0" NewValue="" NewDiec="" NewSuperDiec="" NeedGoods="" NeedValue="110,150" Move="" FuBenID="" Box="" Descriptio="{fac60d}Trade : {17e43e}150 {fac60d}Dice Point for {17e43e}Superior Achievement Badge" Intro="Exchange Point for Superior Achievement Badge" />
  <TreasureEvent ID="2103" Type="2" NewGoods="5041,1,1,0,0,0,0" NewValue="" NewDiec="" NewSuperDiec="" NeedGoods="" NeedValue="110,150" Move="" FuBenID="" Box="" Descriptio="{fac60d}Trade : {17e43e}150 {fac60d}Dice Point for {17e43e}Superior Fame Badge" Intro="Exchange Point for Superior Fame Badge" />
  <TreasureEvent ID="2104" Type="2" NewGoods="7004,1,1,0,0,0,0" NewValue="" NewDiec="" NewSuperDiec="" NeedGoods="" NeedValue="110,150" Move="" FuBenID="" Box="" Descriptio="{fac60d}Trade : {17e43e}150 {fac60d}Dice Point for {17e43e}Epic Chest Ticket" Intro="Exchange Point for Epic Chest Ticket" />
  <TreasureEvent ID="2105" Type="2" NewGoods="7005,1,1,0,0,0,0" NewValue="" NewDiec="" NewSuperDiec="" NeedGoods="" NeedValue="110,150" Move="" FuBenID="" Box="" Descriptio="{fac60d}Trade : {17e43e}150 {fac60d}Dice Point for {17e43e}Epic Pet Ticket" Intro="Exchange Point for Epic Pet Ticket" />
  <TreasureEvent ID="2106" Type="2" NewGoods="5150,1,1,0,0,0,0" NewValue="" NewDiec="" NewSuperDiec="" NeedGoods="" NeedValue="110,150" Move="" FuBenID="" Box="" Descriptio="{fac60d}Trade : {17e43e}150 {fac60d}Dice Point for {17e43e}Medal of Honor" Intro="Exchange Point for Medal of Honor" />
  <TreasureEvent ID="4001" Type="4" NewGoods="" NewValue="110,50" NewDiec="" NewSuperDiec="" NeedGoods="" NeedValue="" Move="" FuBenID="90000" Box="" Descriptio="{fac60d}Boss {f0f0f0}Dice Death King {fac60d}has appeared! Are you prepared to fight?" Intro="Dungeon 1st Floor" />
  <TreasureEvent ID="4002" Type="4" NewGoods="" NewValue="110,50" NewDiec="" NewSuperDiec="" NeedGoods="" NeedValue="" Move="" FuBenID="90001" Box="" Descriptio="{fac60d}Boss {f0f0f0}Dice Wolf King {fac60d}has appeared! Are you prepared to fight?" Intro="Dungeon 2nd Floor" />
  <TreasureEvent ID="4003" Type="4" NewGoods="" NewValue="110,50" NewDiec="" NewSuperDiec="" NeedGoods="" NeedValue="" Move="" FuBenID="90002" Box="" Descriptio="{fac60d}Boss {f0f0f0}Dice Ice Queen {fac60d}has appeared! Are you prepared to fight?" Intro="Dungeon 3rd Floor" />
  <TreasureEvent ID="4004" Type="4" NewGoods="" NewValue="110,50" NewDiec="" NewSuperDiec="" NeedGoods="" NeedValue="" Move="" FuBenID="90003" Box="" Descriptio="{fac60d}Boss {f0f0f0}Dice Gorgon {fac60d}has appeared! Are you prepared to fight?" Intro="Dungeon 4th Floor" />
  <TreasureEvent ID="4005" Type="4" NewGoods="" NewValue="110,50" NewDiec="" NewSuperDiec="" NeedGoods="" NeedValue="" Move="" FuBenID="90004" Box="" Descriptio="{fac60d}Boss {f0f0f0}Dice Balrog {fac60d}has appeared! Are you prepared to fight?" Intro="Dungeon 5th Floor" />
  <TreasureEvent ID="4006" Type="4" NewGoods="" NewValue="110,50" NewDiec="" NewSuperDiec="" NeedGoods="" NeedValue="" Move="" FuBenID="90005" Box="" Descriptio="{fac60d}Boss {f0f0f0}Dice Beam Knight {fac60d}has appeared! Are you prepared to fight?" Intro="Dungeon 6th Floor" />
  <TreasureEvent ID="4007" Type="4" NewGoods="" NewValue="110,50" NewDiec="" NewSuperDiec="" NeedGoods="" NeedValue="" Move="" FuBenID="90006" Box="" Descriptio="{fac60d}Boss {f0f0f0}Dice Zaikan {fac60d}has appeared! Are you prepared to fight?" Intro="Dungeon 7th Floor" />
  <TreasureEvent ID="4008" Type="4" NewGoods="" NewValue="110,50" NewDiec="" NewSuperDiec="" NeedGoods="" NeedValue="" Move="" FuBenID="90007" Box="" Descriptio="{fac60d}Boss {f0f0f0}Dice Hellminer {fac60d}has appeared! Are you prepared to fight?" Intro="Dungeon 8th Floor" />
  <TreasureEvent ID="4009" Type="4" NewGoods="" NewValue="110,50" NewDiec="" NewSuperDiec="" NeedGoods="" NeedValue="" Move="" FuBenID="90008" Box="" Descriptio="{fac60d}Boss {f0f0f0}Dice Kaylon {fac60d}has appeared! Are you prepared to fight?" Intro="Dungeon 9th Floor" />
  <TreasureEvent ID="4010" Type="4" NewGoods="" NewValue="110,50" NewDiec="" NewSuperDiec="" NeedGoods="" NeedValue="" Move="" FuBenID="90009" Box="" Descriptio="{fac60d}Boss {f0f0f0}Dice Nightmare {fac60d}has appeared! Are you prepared to fight?" Intro="Dungeon 10th Floor" />
  <TreasureEvent ID="5001" Type="5" NewGoods="" NewValue="" NewDiec="" NewSuperDiec="" NeedGoods="" NeedValue="" Move="" FuBenID="" Box="3,1|1,1" Descriptio="" Intro="1st Floor Clear Reward" />
  <TreasureEvent ID="5002" Type="5" NewGoods="" NewValue="" NewDiec="" NewSuperDiec="" NeedGoods="" NeedValue="" Move="" FuBenID="" Box="1,1|3,1" Descriptio="" Intro="2nd Floor Clear Reward" />
  <TreasureEvent ID="5003" Type="5" NewGoods="" NewValue="" NewDiec="" NewSuperDiec="" NeedGoods="" NeedValue="" Move="" FuBenID="" Box="1,1|3,1" Descriptio="" Intro="3rd Floor Clear Reward" />
  <TreasureEvent ID="5004" Type="5" NewGoods="" NewValue="" NewDiec="" NewSuperDiec="" NeedGoods="" NeedValue="" Move="" FuBenID="" Box="3,1|1,1" Descriptio="" Intro="4th Floor Clear Reward" />
  <TreasureEvent ID="5005" Type="5" NewGoods="" NewValue="" NewDiec="" NewSuperDiec="" NeedGoods="" NeedValue="" Move="" FuBenID="" Box="1,1|3,1" Descriptio="" Intro="5th Floor Clear Reward" />
  <TreasureEvent ID="5006" Type="5" NewGoods="" NewValue="" NewDiec="" NewSuperDiec="" NeedGoods="" NeedValue="" Move="" FuBenID="" Box="1,1|3,1" Descriptio="" Intro="6th Floor Clear Reward" />
  <TreasureEvent ID="5007" Type="5" NewGoods="" NewValue="" NewDiec="" NewSuperDiec="" NeedGoods="" NeedValue="" Move="" FuBenID="" Box="3,1|1,1" Descriptio="" Intro="7th Floor Clear Reward" />
  <TreasureEvent ID="5008" Type="5" NewGoods="" NewValue="" NewDiec="" NewSuperDiec="" NeedGoods="" NeedValue="" Move="" FuBenID="" Box="1,1|3,1" Descriptio="" Intro="8th Floor Clear Reward" />
  <TreasureEvent ID="5009" Type="5" NewGoods="" NewValue="" NewDiec="" NewSuperDiec="" NeedGoods="" NeedValue="" Move="" FuBenID="" Box="1,1|3,1" Descriptio="" Intro="9th Floor Clear Reward" />
  <TreasureEvent ID="5010" Type="5" NewGoods="" NewValue="" NewDiec="" NewSuperDiec="" NeedGoods="" NeedValue="" Move="" FuBenID="" Box="3,2|2,1|3,2" Descriptio="" Intro="10th Floor Clear Reward" />
</Config>